{"version": "1", "message": "ERROR: Hidden Testcases server unreachable.", "problem_id": "ads1_m12_a1", "user_id": "ChaitanyaPuritipati", "score": {"sample": {"0": {"execution_time": 0.39200520515441895, "passed": true}, "1": {"execution_time": 0.2932133674621582, "passed": true}, "2": {"execution_time": 0.3308098316192627, "passed": true}, "3": {"execution_time": 0.3121678829193115, "passed": true}, "4": {"execution_time": 0.3129158020019531, "passed": true}, "5": {"execution_time": 0.3241863250732422, "passed": true}}}, "check_style_score": "1/1"}